qDNA/__init__.py
qDNA/defaults.yaml
qDNA/legacy.py
qDNA/qDNA-default.mplstyle
qDNA/data/options.json
qDNA/data/qDNA.log
qDNA/data/tb_models_props.json
qDNA/data/color_palettes/matplotlib.json
qDNA/data/color_palettes/nature.json
qDNA/data/color_palettes/seaborn.json
qDNA/data/lcao_params/HKS.json
qDNA/data/lcao_params/MMTS.json
qDNA/data/lcao_params/MSF.json
qDNA/data/lcao_params/SN.json
qDNA/data/lcao_params/SN_all.json
qDNA/data/raw/comp_time.json
qDNA/data/raw/data_paper/dipole_7bp_J0.5.json
qDNA/data/raw/data_paper/dipole_7bp_J0.json
qDNA/data/raw/data_paper/dipole_7bp_J1.json
qDNA/data/raw/data_paper/lifetime_4bp_relax0.01.json
qDNA/data/raw/data_paper/lifetime_4bp_relax0.02.json
qDNA/data/raw/data_paper/lifetime_4bp_relax0.05.json
qDNA/data/raw/data_paper/lifetime_7bp_J0.5.json
qDNA/data/raw/data_paper/lifetime_7bp_J0.json
qDNA/data/raw/data_paper/lifetime_7bp_J1.json
qDNA/data/raw/figures_paper/Fig_1.pdf
qDNA/data/raw/figures_paper/Fig_2.pdf
qDNA/data/raw/figures_paper/Fig_3.pdf
qDNA/data/raw/figures_paper/Fig_3a.pdf
qDNA/data/raw/figures_paper/Fig_3b.pdf
qDNA/data/raw/figures_paper/Fig_4.pdf
qDNA/data/raw/figures_paper/Fig_5a.pdf
qDNA/data/raw/figures_paper/Fig_5b.pdf
qDNA/data/raw/figures_paper/Fig_6.pdf
qDNA/data/raw/figures_paper/Fig_7.pdf
qDNA/data/raw/figures_paper/Fig_8a.pdf
qDNA/data/raw/figures_paper/Fig_8b.pdf
qDNA/data/raw/figures_paper/Fig_S1.pdf
qDNA/data/raw/figures_paper/Fig_S2.pdf
qDNA/data/raw/figures_paper/Fig_S3a.pdf
qDNA/data/raw/figures_paper/Fig_S3b.pdf
qDNA/data/raw/figures_paper/Fig_S4.pdf
qDNA/data/raw/figures_paper/Fig_S5.pdf
qDNA/data/raw/figures_tutorials/FMO_energy_level.png
qDNA/data/raw/figures_tutorials/Fig_1.png
qDNA/data/raw/figures_tutorials/Fig_2.png
qDNA/data/raw/figures_tutorials/base_translation_rotation.png
qDNA/data/tb_params/1BNA_ELM.json
qDNA/data/tb_params/Bittner2007_ELM.json
qDNA/data/tb_params/Endres2002_WM.json
qDNA/data/tb_params/Hawke2010_ELM.json
qDNA/data/tb_params/Hawke2010_LM.json
qdna-1.0.1.dist-info/licenses/LICENSE.txt
qdna-1.0.1.dist-info/METADATA
qdna-1.0.1.dist-info/WHEEL
qdna-1.0.1.dist-info/top_level.txt
qdna-1.0.1.dist-info/RECORD
