Metadata-Version: 2.4
Name: qDNA
Version: 1.0.1
Summary: QuantumDNA is an open-source Python package for simulating energy and charge transfer in DNA using quantum mechanical methods.
Author-email: Dennis Herb <dennis.herb@uni-ulm.de>
License: BSD-3-Clause
Project-URL: documentation, https://quantumdna.readthedocs.io/en/latest/
Project-URL: repository, https://github.com/dehe1011/QuantumDNA
Project-URL: tutorials, https://github.com/dehe1011/QuantumDNA-notebooks
Classifier: Intended Audience :: Science/Research
Classifier: License :: OSI Approved :: BSD License
Classifier: Programming Language :: Python :: 3
Requires-Python: >=3.8
License-File: LICENSE.txt
Requires-Dist: customtkinter
Requires-Dist: matplotlib
Requires-Dist: openpyxl
Requires-Dist: pandas
Requires-Dist: pyyaml
Requires-Dist: qutip
Requires-Dist: seaborn
Requires-Dist: tqdm
Provides-Extra: dev
Requires-Dist: black; extra == "dev"
Requires-Dist: build; extra == "dev"
Requires-Dist: coverage; extra == "dev"
Requires-Dist: coveralls; extra == "dev"
Requires-Dist: docformatter; extra == "dev"
Requires-Dist: mypy; extra == "dev"
Requires-Dist: pre-commit; extra == "dev"
Requires-Dist: pylint; extra == "dev"
Requires-Dist: pytest; extra == "dev"
Requires-Dist: setuptools; extra == "dev"
Requires-Dist: twine; extra == "dev"
Requires-Dist: wheel; extra == "dev"
Provides-Extra: docs
Requires-Dist: ipykernel; extra == "docs"
Requires-Dist: nbsphinx; extra == "docs"
Requires-Dist: numpydoc; extra == "docs"
Requires-Dist: sphinx>=3.0; extra == "docs"
Requires-Dist: sphinx-codeautolink; extra == "docs"
Requires-Dist: sphinx_rtd_theme; extra == "docs"
Requires-Dist: sphinxcontrib-bibtex>=2.1; extra == "docs"
Requires-Dist: sphinxcontrib-svg2pdfconverter; extra == "docs"
Dynamic: license-file
